liveramp_autoamtion/allure_util.py
liveramp_autoamtion/logger.py
liveramp_autoamtion/login_util.py
liveramp_autoamtion/parsers.py
liveramp_autoamtion/playwright_util.py
liveramp_autoamtion/read_report.py
liveramp_autoamtion/request_util.py
liveramp_autoamtion/selenium_util.py
liveramp_autoamtion/time_util.py
liveramp_autoamtion/upload_util.py
liveramp_automation_framework-1.0.dist-info/METADATA
liveramp_automation_framework-1.0.dist-info/WHEEL
liveramp_automation_framework-1.0.dist-info/top_level.txt
liveramp_automation_framework-1.0.dist-info/RECORD
