Metadata-Version: 2.1
Name: liveramp-automation-framework
Version: 1.0
Summary: liveramp_automation_framework
Author: Jasmine Qian
Author-email: jasmine.qian@liveramp.com
Requires-Dist: pytest
Requires-Dist: pytest-bdd
Requires-Dist: pytest-playwright
Requires-Dist: allure-pytest-bdd
Requires-Dist: allure-python-commons
Requires-Dist: google
Requires-Dist: google-api-core
Requires-Dist: google-auth
Requires-Dist: google-cloud-bigquery
Requires-Dist: google-cloud-core
Requires-Dist: google-cloud-storage
Requires-Dist: google-crc32c
Requires-Dist: google-resumable-media
Requires-Dist: googleapis-common-protos
Requires-Dist: PyYAML
Requires-Dist: pytest-json-report
Requires-Dist: pytest-json
Requires-Dist: pytest-xdist
Requires-Dist: requests
